debugpy/ThirdPartyNotices.txt
debugpy/__init__.py
debugpy/__main__.py
debugpy/_version.py
debugpy/public_api.py
debugpy/py.typed
debugpy/_vendored/__init__.py
debugpy/_vendored/_pydevd_packaging.py
debugpy/_vendored/_util.py
debugpy/_vendored/force_pydevd.py
debugpy/_vendored/pydevd/pydev_app_engine_debug_startup.py
debugpy/_vendored/pydevd/pydev_coverage.py
debugpy/_vendored/pydevd/pydev_pysrc.py
debugpy/_vendored/pydevd/pydev_run_in_console.py
debugpy/_vendored/pydevd/pydevconsole.py
debugpy/_vendored/pydevd/pydevd.py
debugpy/_vendored/pydevd/pydevd_file_utils.py
debugpy/_vendored/pydevd/pydevd_tracing.py
debugpy/_vendored/pydevd/setup_pydevd_cython.py
debugpy/_vendored/pydevd/_pydev_bundle/__init__.py
debugpy/_vendored/pydevd/_pydev_bundle/_pydev_calltip_util.py
debugpy/_vendored/pydevd/_pydev_bundle/_pydev_completer.py
debugpy/_vendored/pydevd/_pydev_bundle/_pydev_execfile.py
debugpy/_vendored/pydevd/_pydev_bundle/_pydev_filesystem_encoding.py
debugpy/_vendored/pydevd/_pydev_bundle/_pydev_getopt.py
debugpy/_vendored/pydevd/_pydev_bundle/_pydev_imports_tipper.py
debugpy/_vendored/pydevd/_pydev_bundle/_pydev_jy_imports_tipper.py
debugpy/_vendored/pydevd/_pydev_bundle/_pydev_log.py
debugpy/_vendored/pydevd/_pydev_bundle/_pydev_saved_modules.py
debugpy/_vendored/pydevd/_pydev_bundle/_pydev_sys_patch.py
debugpy/_vendored/pydevd/_pydev_bundle/_pydev_tipper_common.py
debugpy/_vendored/pydevd/_pydev_bundle/pydev_console_utils.py
debugpy/_vendored/pydevd/_pydev_bundle/pydev_import_hook.py
debugpy/_vendored/pydevd/_pydev_bundle/pydev_imports.py
debugpy/_vendored/pydevd/_pydev_bundle/pydev_ipython_console.py
debugpy/_vendored/pydevd/_pydev_bundle/pydev_ipython_console_011.py
debugpy/_vendored/pydevd/_pydev_bundle/pydev_is_thread_alive.py
debugpy/_vendored/pydevd/_pydev_bundle/pydev_localhost.py
debugpy/_vendored/pydevd/_pydev_bundle/pydev_log.py
debugpy/_vendored/pydevd/_pydev_bundle/pydev_monkey.py
debugpy/_vendored/pydevd/_pydev_bundle/pydev_monkey_qt.py
debugpy-1.8.20.dist-info/licenses/LICENSE
debugpy-1.8.20.dist-info/METADATA
debugpy-1.8.20.dist-info/WHEEL
debugpy-1.8.20.dist-info/entry_points.txt
debugpy-1.8.20.dist-info/top_level.txt
debugpy-1.8.20.dist-info/RECORD
