Metadata-Version: 2.1
Name: debugpy
Version: 1.8.20
Summary: An implementation of the Debug Adapter Protocol for Python
Home-page: https://aka.ms/debugpy
Author: Microsoft Corporation
Author-email: ptvshelp@microsoft.com
License: MIT
Project-URL: Source, https://github.com/microsoft/debugpy
Classifier: Development Status :: 5 - Production/Stable
Classifier: Programming Language :: Python :: 3.8
Classifier: Programming Language :: Python :: 3.9
Classifier: Programming Language :: Python :: 3.10
Classifier: Programming Language :: Python :: 3.11
Classifier: Programming Language :: Python :: 3.12
Classifier: Programming Language :: Python :: 3.13
Classifier: Programming Language :: Python :: 3.14
Classifier: Topic :: Software Development :: Debuggers
Classifier: Operating System :: Microsoft :: Windows
Classifier: Operating System :: MacOS
Classifier: Operating System :: POSIX
Classifier: License :: OSI Approved :: MIT License
Requires-Python: >=3.8
License-File: LICENSE
